otel_metric_base/__init__.py
otel_metric_base/otel_metrics.py
otel_metric_base-0.1.1.dist-info/LICENSE
otel_metric_base-0.1.1.dist-info/METADATA
otel_metric_base-0.1.1.dist-info/WHEEL
otel_metric_base-0.1.1.dist-info/top_level.txt
otel_metric_base-0.1.1.dist-info/RECORD
