Metadata-Version: 2.1
Name: otel-metric-base
Version: 0.1.1
Summary: An OpenTelemetry metrics integration module.
Author-email: Brian Hartford <bh419@protonmail.com>
License: Apache-2.0
Project-URL: Homepage, https://github.com/UTXOnly/OTel-metric-base
Project-URL: Repository, https://github.com/UTXOnly/OTel-metric-base
Keywords: OpenTelemetry,Metrics,OTLP,Python
Classifier: Development Status :: 3 - Alpha
Classifier: Intended Audience :: Developers
Classifier: License :: OSI Approved :: Apache Software License
Classifier: Programming Language :: Python :: 3
Classifier: Programming Language :: Python :: 3.6
Classifier: Programming Language :: Python :: 3.7
Classifier: Programming Language :: Python :: 3.8
Classifier: Programming Language :: Python :: 3.9
Classifier: Programming Language :: Python :: 3.10
Classifier: Programming Language :: Python :: 3.11
Requires-Python: >=3.6
License-File: LICENSE
Requires-Dist: opentelemetry-api
Requires-Dist: opentelemetry-sdk
Requires-Dist: opentelemetry-exporter-otlp-proto-grpc
